[{"id": "9193131278467", "title": "New 20-inch Suitcase, Large Deep Compartment Suitcase, Side-opening Suitcase, With External Storage Bag, Wheeled Luggage, Cabin Bag, Silent Swivel Wheels, Combination Lock Travel Bag", "price": 999, "image": "https://cdn.shopify.com/s/files/1/0735/9404/4547/files/4c8eaafe-ff7b-4bc9-9efd-cc4c0e50f90c.jpg?v=1784287410", "variants": 5, "images": 1}, {"id": "9193133047939", "title": "20 Inch Detachable Suitcase, Children's Suitcase, Cycling Luggage, Handcart Luggage, TSA Lock, Universal Wheel Multifunctional Lockable Rolling Suitcase, With USB Port, Suitable For Travel", "price": 999, "image": "https://cdn.shopify.com/s/files/1/0735/9404/4547/files/05a87350-cce5-4fb3-ae37-773fd127001c.jpg?v=1784287459", "variants": 5, "images": 1}, {"id": "9193136521347", "title": "20 Inch Double Pull Rod Design Luggage Case, Can Be Seated, Front Open Lid Luggage Compartment, Silent Universal Wheels, Dry Wet Separation, T-shaped Pull Rod Travel Box", "price": 999, "image": "https://cdn.shopify.com/s/files/1/0735/9404/4547/files/8a2547b7-3bcc-43dc-b189-9c421ff5c303.png?v=1784287573", "variants": 5, "images": 1}]