[{"id": "9193058173059", "title": "Pattern-printed Cotton T-shirts For Men And Women", "price": 6.47, "image": "https://cdn.shopify.com/s/files/1/0735/9404/4547/files/f2997a34-7cd5-499b-a83d-1b809437b108.jpg?v=1784286058", "variants": 3, "images": 2}, {"id": "9193068265603", "title": "Mercerized Cotton Thin Unisex Top", "price": 6.47, "image": "https://cdn.shopify.com/s/files/1/0735/9404/4547/files/0d5c5e6d-9784-4fdf-90a7-d14970b71d12_fine.jpg?v=1784286210", "variants": 3, "images": 3}, {"id": "9193078423683", "title": "Mens Casual Loose-Fit Mesh Short-Sleeve T-Shirt", "price": 2.81, "image": "https://cdn.shopify.com/s/files/1/0735/9404/4547/files/3f094bc0-3501-4204-aeee-24a92a6275a1.jpg?v=1784286386", "variants": 3, "images": 2}]